gamejoltapi.py
gamejoltapi-0.0.3.dist-info/LICENSE
gamejoltapi-0.0.3.dist-info/METADATA
gamejoltapi-0.0.3.dist-info/WHEEL
gamejoltapi-0.0.3.dist-info/top_level.txt
gamejoltapi-0.0.3.dist-info/RECORD
