Metadata-Version: 2.1
Name: gamejoltapi
Version: 0.0.3
Summary: Single threaded Python wrapper for the Game Jolt API running through HTTP requests
Home-page: https://github.com/bgempire/gamejoltapi
Author: Joel Gomes da Silva
Author-email: joelgomes1994@hotmail.com
License: MIT
Keywords: game jolt gamedev api wrapper interface gamejolt gamejoltapi
Platform: UNKNOWN
Classifier: Development Status :: 5 - Production/Stable
Classifier: Intended Audience :: Developers
Classifier: License :: OSI Approved :: MIT License
Classifier: Operating System :: OS Independent
Classifier: Programming Language :: Python :: 3 :: Only
Classifier: Topic :: Games/Entertainment
Classifier: Topic :: Software Development :: Libraries
